{"validation_mean": 0.2578125, "time_this_iter_s": 3.247978448867798, "done": false, "timesteps_total": null, "episodes_total": null, "training_iteration": 1, "trial_id": "66323_00052", "experiment_id": "38f4798ce7e7460ab9a78ba6362034f1", "date": "2022-08-13_18-34-30", "timestamp": 1660386870, "time_total_s": 3.247978448867798, "pid": 126273, "hostname": "localhost.localdomain", "node_ip": "192.168.249.74", "config": {"lr": 1.9538989575826076e-05, "batch_size": 64, "beta1": 0.9, "beta2": 0.999, "weight_decay": 0.009198113639144518}, "time_since_restore": 3.247978448867798, "timesteps_since_restore": 0, "iterations_since_restore": 1}
{"validation_mean": 0.6369460444339955, "time_this_iter_s": 202.19810271263123, "done": false, "timesteps_total": null, "episodes_total": null, "training_iteration": 2, "trial_id": "66323_00052", "experiment_id": "38f4798ce7e7460ab9a78ba6362034f1", "date": "2022-08-13_18-37-53", "timestamp": 1660387073, "time_total_s": 205.44608116149902, "pid": 126273, "hostname": "localhost.localdomain", "node_ip": "192.168.249.74", "config": {"lr": 1.9538989575826076e-05, "batch_size": 64, "beta1": 0.9, "beta2": 0.999, "weight_decay": 0.009198113639144518}, "time_since_restore": 205.44608116149902, "timesteps_since_restore": 0, "iterations_since_restore": 2}
{"validation_mean": 0.6538732808275538, "time_this_iter_s": 206.14251375198364, "done": false, "timesteps_total": null, "episodes_total": null, "training_iteration": 3, "trial_id": "66323_00052", "experiment_id": "38f4798ce7e7460ab9a78ba6362034f1", "date": "2022-08-13_18-41-19", "timestamp": 1660387279, "time_total_s": 411.58859491348267, "pid": 126273, "hostname": "localhost.localdomain", "node_ip": "192.168.249.74", "config": {"lr": 1.9538989575826076e-05, "batch_size": 64, "beta1": 0.9, "beta2": 0.999, "weight_decay": 0.009198113639144518}, "time_since_restore": 411.58859491348267, "timesteps_since_restore": 0, "iterations_since_restore": 3}
{"validation_mean": 0.6857293993182085, "time_this_iter_s": 206.75579190254211, "done": false, "timesteps_total": null, "episodes_total": null, "training_iteration": 4, "trial_id": "66323_00052", "experiment_id": "38f4798ce7e7460ab9a78ba6362034f1", "date": "2022-08-13_18-44-45", "timestamp": 1660387485, "time_total_s": 618.3443868160248, "pid": 126273, "hostname": "localhost.localdomain", "node_ip": "192.168.249.74", "config": {"lr": 1.9538989575826076e-05, "batch_size": 64, "beta1": 0.9, "beta2": 0.999, "weight_decay": 0.009198113639144518}, "time_since_restore": 618.3443868160248, "timesteps_since_restore": 0, "iterations_since_restore": 4}
{"validation_mean": 0.7359233572352181, "time_this_iter_s": 206.9731321334839, "done": false, "timesteps_total": null, "episodes_total": null, "training_iteration": 5, "trial_id": "66323_00052", "experiment_id": "38f4798ce7e7460ab9a78ba6362034f1", "date": "2022-08-13_18-48-12", "timestamp": 1660387692, "time_total_s": 825.3175189495087, "pid": 126273, "hostname": "localhost.localdomain", "node_ip": "192.168.249.74", "config": {"lr": 1.9538989575826076e-05, "batch_size": 64, "beta1": 0.9, "beta2": 0.999, "weight_decay": 0.009198113639144518}, "time_since_restore": 825.3175189495087, "timesteps_since_restore": 0, "iterations_since_restore": 5}
{"validation_mean": 0.7212295756435876, "time_this_iter_s": 206.62064123153687, "done": false, "timesteps_total": null, "episodes_total": null, "training_iteration": 6, "trial_id": "66323_00052", "experiment_id": "38f4798ce7e7460ab9a78ba6362034f1", "date": "2022-08-13_18-51-39", "timestamp": 1660387899, "time_total_s": 1031.9381601810455, "pid": 126273, "hostname": "localhost.localdomain", "node_ip": "192.168.249.74", "config": {"lr": 1.9538989575826076e-05, "batch_size": 64, "beta1": 0.9, "beta2": 0.999, "weight_decay": 0.009198113639144518}, "time_since_restore": 1031.9381601810455, "timesteps_since_restore": 0, "iterations_since_restore": 6}
{"validation_mean": 0.746385329728459, "time_this_iter_s": 205.68164610862732, "done": false, "timesteps_total": null, "episodes_total": null, "training_iteration": 7, "trial_id": "66323_00052", "experiment_id": "38f4798ce7e7460ab9a78ba6362034f1", "date": "2022-08-13_18-55-05", "timestamp": 1660388105, "time_total_s": 1237.6198062896729, "pid": 126273, "hostname": "localhost.localdomain", "node_ip": "192.168.249.74", "config": {"lr": 1.9538989575826076e-05, "batch_size": 64, "beta1": 0.9, "beta2": 0.999, "weight_decay": 0.009198113639144518}, "time_since_restore": 1237.6198062896729, "timesteps_since_restore": 0, "iterations_since_restore": 7}
{"validation_mean": 0.7505583637004819, "time_this_iter_s": 205.55115842819214, "done": true, "timesteps_total": null, "episodes_total": null, "training_iteration": 8, "trial_id": "66323_00052", "experiment_id": "38f4798ce7e7460ab9a78ba6362034f1", "date": "2022-08-13_18-58-30", "timestamp": 1660388310, "time_total_s": 1443.170964717865, "pid": 126273, "hostname": "localhost.localdomain", "node_ip": "192.168.249.74", "config": {"lr": 1.9538989575826076e-05, "batch_size": 64, "beta1": 0.9, "beta2": 0.999, "weight_decay": 0.009198113639144518}, "time_since_restore": 1443.170964717865, "timesteps_since_restore": 0, "iterations_since_restore": 8}
