{"validation_mean": 0.2578125, "time_this_iter_s": 3.535156488418579, "done": false, "timesteps_total": null, "episodes_total": null, "training_iteration": 1, "trial_id": "a5270_00024", "experiment_id": "b4e564bfe4bd43e3bbadaaaad79855f0", "date": "2022-08-13_09-01-42", "timestamp": 1660352502, "time_total_s": 3.535156488418579, "pid": 128228, "hostname": "localhost.localdomain", "node_ip": "192.168.249.74", "config": {"lr": 3.448496205595341e-05, "batch_size": 64, "beta1": 0.9, "beta2": 0.999, "weight_decay": 0.006519728814948943}, "time_since_restore": 3.535156488418579, "timesteps_since_restore": 0, "iterations_since_restore": 1}
{"validation_mean": 0.682966968378982, "time_this_iter_s": 667.323338508606, "done": false, "timesteps_total": null, "episodes_total": null, "training_iteration": 2, "trial_id": "a5270_00024", "experiment_id": "b4e564bfe4bd43e3bbadaaaad79855f0", "date": "2022-08-13_09-12-49", "timestamp": 1660353169, "time_total_s": 670.8584949970245, "pid": 128228, "hostname": "localhost.localdomain", "node_ip": "192.168.249.74", "config": {"lr": 3.448496205595341e-05, "batch_size": 64, "beta1": 0.9, "beta2": 0.999, "weight_decay": 0.006519728814948943}, "time_since_restore": 670.8584949970245, "timesteps_since_restore": 0, "iterations_since_restore": 2}
{"validation_mean": 0.7167038909133655, "time_this_iter_s": 682.8654103279114, "done": false, "timesteps_total": null, "episodes_total": null, "training_iteration": 3, "trial_id": "a5270_00024", "experiment_id": "b4e564bfe4bd43e3bbadaaaad79855f0", "date": "2022-08-13_09-24-12", "timestamp": 1660353852, "time_total_s": 1353.723905324936, "pid": 128228, "hostname": "localhost.localdomain", "node_ip": "192.168.249.74", "config": {"lr": 3.448496205595341e-05, "batch_size": 64, "beta1": 0.9, "beta2": 0.999, "weight_decay": 0.006519728814948943}, "time_since_restore": 1353.723905324936, "timesteps_since_restore": 0, "iterations_since_restore": 3}
{"validation_mean": 0.7619019630892206, "time_this_iter_s": 677.3232054710388, "done": false, "timesteps_total": null, "episodes_total": null, "training_iteration": 4, "trial_id": "a5270_00024", "experiment_id": "b4e564bfe4bd43e3bbadaaaad79855f0", "date": "2022-08-13_09-35-29", "timestamp": 1660354529, "time_total_s": 2031.0471107959747, "pid": 128228, "hostname": "localhost.localdomain", "node_ip": "192.168.249.74", "config": {"lr": 3.448496205595341e-05, "batch_size": 64, "beta1": 0.9, "beta2": 0.999, "weight_decay": 0.006519728814948943}, "time_since_restore": 2031.0471107959747, "timesteps_since_restore": 0, "iterations_since_restore": 4}
{"validation_mean": 0.7456800282120607, "time_this_iter_s": 680.1006708145142, "done": false, "timesteps_total": null, "episodes_total": null, "training_iteration": 5, "trial_id": "a5270_00024", "experiment_id": "b4e564bfe4bd43e3bbadaaaad79855f0", "date": "2022-08-13_09-46-49", "timestamp": 1660355209, "time_total_s": 2711.147781610489, "pid": 128228, "hostname": "localhost.localdomain", "node_ip": "192.168.249.74", "config": {"lr": 3.448496205595341e-05, "batch_size": 64, "beta1": 0.9, "beta2": 0.999, "weight_decay": 0.006519728814948943}, "time_since_restore": 2711.147781610489, "timesteps_since_restore": 0, "iterations_since_restore": 5}
{"validation_mean": 0.7828259080757024, "time_this_iter_s": 668.3889677524567, "done": false, "timesteps_total": null, "episodes_total": null, "training_iteration": 6, "trial_id": "a5270_00024", "experiment_id": "b4e564bfe4bd43e3bbadaaaad79855f0", "date": "2022-08-13_09-57-58", "timestamp": 1660355878, "time_total_s": 3379.5367493629456, "pid": 128228, "hostname": "localhost.localdomain", "node_ip": "192.168.249.74", "config": {"lr": 3.448496205595341e-05, "batch_size": 64, "beta1": 0.9, "beta2": 0.999, "weight_decay": 0.006519728814948943}, "time_since_restore": 3379.5367493629456, "timesteps_since_restore": 0, "iterations_since_restore": 6}
{"validation_mean": 0.7721288350769954, "time_this_iter_s": 669.6983625888824, "done": false, "timesteps_total": null, "episodes_total": null, "training_iteration": 7, "trial_id": "a5270_00024", "experiment_id": "b4e564bfe4bd43e3bbadaaaad79855f0", "date": "2022-08-13_10-09-07", "timestamp": 1660356547, "time_total_s": 4049.235111951828, "pid": 128228, "hostname": "localhost.localdomain", "node_ip": "192.168.249.74", "config": {"lr": 3.448496205595341e-05, "batch_size": 64, "beta1": 0.9, "beta2": 0.999, "weight_decay": 0.006519728814948943}, "time_since_restore": 4049.235111951828, "timesteps_since_restore": 0, "iterations_since_restore": 7}
{"validation_mean": 0.7777712472081815, "time_this_iter_s": 666.5994668006897, "done": false, "timesteps_total": null, "episodes_total": null, "training_iteration": 8, "trial_id": "a5270_00024", "experiment_id": "b4e564bfe4bd43e3bbadaaaad79855f0", "date": "2022-08-13_10-20-14", "timestamp": 1660357214, "time_total_s": 4715.834578752518, "pid": 128228, "hostname": "localhost.localdomain", "node_ip": "192.168.249.74", "config": {"lr": 3.448496205595341e-05, "batch_size": 64, "beta1": 0.9, "beta2": 0.999, "weight_decay": 0.006519728814948943}, "time_since_restore": 4715.834578752518, "timesteps_since_restore": 0, "iterations_since_restore": 8}
{"validation_mean": 0.7864111907840602, "time_this_iter_s": 667.5127489566803, "done": false, "timesteps_total": null, "episodes_total": null, "training_iteration": 9, "trial_id": "a5270_00024", "experiment_id": "b4e564bfe4bd43e3bbadaaaad79855f0", "date": "2022-08-13_10-31-21", "timestamp": 1660357881, "time_total_s": 5383.347327709198, "pid": 128228, "hostname": "localhost.localdomain", "node_ip": "192.168.249.74", "config": {"lr": 3.448496205595341e-05, "batch_size": 64, "beta1": 0.9, "beta2": 0.999, "weight_decay": 0.006519728814948943}, "time_since_restore": 5383.347327709198, "timesteps_since_restore": 0, "iterations_since_restore": 9}
{"validation_mean": 0.7959915363818032, "time_this_iter_s": 677.1261417865753, "done": false, "timesteps_total": null, "episodes_total": null, "training_iteration": 10, "trial_id": "a5270_00024", "experiment_id": "b4e564bfe4bd43e3bbadaaaad79855f0", "date": "2022-08-13_10-42-39", "timestamp": 1660358559, "time_total_s": 6060.473469495773, "pid": 128228, "hostname": "localhost.localdomain", "node_ip": "192.168.249.74", "config": {"lr": 3.448496205595341e-05, "batch_size": 64, "beta1": 0.9, "beta2": 0.999, "weight_decay": 0.006519728814948943}, "time_since_restore": 6060.473469495773, "timesteps_since_restore": 0, "iterations_since_restore": 10}
{"validation_mean": 0.7756553426589867, "time_this_iter_s": 671.662056684494, "done": false, "timesteps_total": null, "episodes_total": null, "training_iteration": 11, "trial_id": "a5270_00024", "experiment_id": "b4e564bfe4bd43e3bbadaaaad79855f0", "date": "2022-08-13_10-53-50", "timestamp": 1660359230, "time_total_s": 6732.135526180267, "pid": 128228, "hostname": "localhost.localdomain", "node_ip": "192.168.249.74", "config": {"lr": 3.448496205595341e-05, "batch_size": 64, "beta1": 0.9, "beta2": 0.999, "weight_decay": 0.006519728814948943}, "time_since_restore": 6732.135526180267, "timesteps_since_restore": 0, "iterations_since_restore": 11}
{"validation_mean": 0.7852356882567297, "time_this_iter_s": 669.79736161232, "done": false, "timesteps_total": null, "episodes_total": null, "training_iteration": 12, "trial_id": "a5270_00024", "experiment_id": "b4e564bfe4bd43e3bbadaaaad79855f0", "date": "2022-08-13_11-05-00", "timestamp": 1660359900, "time_total_s": 7401.932887792587, "pid": 128228, "hostname": "localhost.localdomain", "node_ip": "192.168.249.74", "config": {"lr": 3.448496205595341e-05, "batch_size": 64, "beta1": 0.9, "beta2": 0.999, "weight_decay": 0.006519728814948943}, "time_since_restore": 7401.932887792587, "timesteps_since_restore": 0, "iterations_since_restore": 12}
{"validation_mean": 0.7740684142470906, "time_this_iter_s": 670.4922893047333, "done": false, "timesteps_total": null, "episodes_total": null, "training_iteration": 13, "trial_id": "a5270_00024", "experiment_id": "b4e564bfe4bd43e3bbadaaaad79855f0", "date": "2022-08-13_11-16-11", "timestamp": 1660360571, "time_total_s": 8072.425177097321, "pid": 128228, "hostname": "localhost.localdomain", "node_ip": "192.168.249.74", "config": {"lr": 3.448496205595341e-05, "batch_size": 64, "beta1": 0.9, "beta2": 0.999, "weight_decay": 0.006519728814948943}, "time_since_restore": 8072.425177097321, "timesteps_since_restore": 0, "iterations_since_restore": 13}
{"validation_mean": 0.7922887034207123, "time_this_iter_s": 668.9087407588959, "done": false, "timesteps_total": null, "episodes_total": null, "training_iteration": 14, "trial_id": "a5270_00024", "experiment_id": "b4e564bfe4bd43e3bbadaaaad79855f0", "date": "2022-08-13_11-27-19", "timestamp": 1660361239, "time_total_s": 8741.333917856216, "pid": 128228, "hostname": "localhost.localdomain", "node_ip": "192.168.249.74", "config": {"lr": 3.448496205595341e-05, "batch_size": 64, "beta1": 0.9, "beta2": 0.999, "weight_decay": 0.006519728814948943}, "time_since_restore": 8741.333917856216, "timesteps_since_restore": 0, "iterations_since_restore": 14}
{"validation_mean": 0.7757728929117198, "time_this_iter_s": 667.2118256092072, "done": false, "timesteps_total": null, "episodes_total": null, "training_iteration": 15, "trial_id": "a5270_00024", "experiment_id": "b4e564bfe4bd43e3bbadaaaad79855f0", "date": "2022-08-13_11-38-27", "timestamp": 1660361907, "time_total_s": 9408.545743465424, "pid": 128228, "hostname": "localhost.localdomain", "node_ip": "192.168.249.74", "config": {"lr": 3.448496205595341e-05, "batch_size": 64, "beta1": 0.9, "beta2": 0.999, "weight_decay": 0.006519728814948943}, "time_since_restore": 9408.545743465424, "timesteps_since_restore": 0, "iterations_since_restore": 15}
{"validation_mean": 0.7931703303162102, "time_this_iter_s": 666.8865783214569, "done": false, "timesteps_total": null, "episodes_total": null, "training_iteration": 16, "trial_id": "a5270_00024", "experiment_id": "b4e564bfe4bd43e3bbadaaaad79855f0", "date": "2022-08-13_11-49-34", "timestamp": 1660362574, "time_total_s": 10075.43232178688, "pid": 128228, "hostname": "localhost.localdomain", "node_ip": "192.168.249.74", "config": {"lr": 3.448496205595341e-05, "batch_size": 64, "beta1": 0.9, "beta2": 0.999, "weight_decay": 0.006519728814948943}, "time_since_restore": 10075.43232178688, "timesteps_since_restore": 0, "iterations_since_restore": 16}
{"validation_mean": 0.7877042435641237, "time_this_iter_s": 666.4414799213409, "done": false, "timesteps_total": null, "episodes_total": null, "training_iteration": 17, "trial_id": "a5270_00024", "experiment_id": "b4e564bfe4bd43e3bbadaaaad79855f0", "date": "2022-08-13_12-00-40", "timestamp": 1660363240, "time_total_s": 10741.873801708221, "pid": 128228, "hostname": "localhost.localdomain", "node_ip": "192.168.249.74", "config": {"lr": 3.448496205595341e-05, "batch_size": 64, "beta1": 0.9, "beta2": 0.999, "weight_decay": 0.006519728814948943}, "time_since_restore": 10741.873801708221, "timesteps_since_restore": 0, "iterations_since_restore": 17}
{"validation_mean": 0.7997531444692606, "time_this_iter_s": 672.2693033218384, "done": false, "timesteps_total": null, "episodes_total": null, "training_iteration": 18, "trial_id": "a5270_00024", "experiment_id": "b4e564bfe4bd43e3bbadaaaad79855f0", "date": "2022-08-13_12-11-52", "timestamp": 1660363912, "time_total_s": 11414.14310503006, "pid": 128228, "hostname": "localhost.localdomain", "node_ip": "192.168.249.74", "config": {"lr": 3.448496205595341e-05, "batch_size": 64, "beta1": 0.9, "beta2": 0.999, "weight_decay": 0.006519728814948943}, "time_since_restore": 11414.14310503006, "timesteps_since_restore": 0, "iterations_since_restore": 18}
{"validation_mean": 0.7875866933113906, "time_this_iter_s": 672.6780831813812, "done": false, "timesteps_total": null, "episodes_total": null, "training_iteration": 19, "trial_id": "a5270_00024", "experiment_id": "b4e564bfe4bd43e3bbadaaaad79855f0", "date": "2022-08-13_12-23-05", "timestamp": 1660364585, "time_total_s": 12086.821188211441, "pid": 128228, "hostname": "localhost.localdomain", "node_ip": "192.168.249.74", "config": {"lr": 3.448496205595341e-05, "batch_size": 64, "beta1": 0.9, "beta2": 0.999, "weight_decay": 0.006519728814948943}, "time_since_restore": 12086.821188211441, "timesteps_since_restore": 0, "iterations_since_restore": 19}
{"validation_mean": 0.7918772775361467, "time_this_iter_s": 669.3595192432404, "done": false, "timesteps_total": null, "episodes_total": null, "training_iteration": 20, "trial_id": "a5270_00024", "experiment_id": "b4e564bfe4bd43e3bbadaaaad79855f0", "date": "2022-08-13_12-34-14", "timestamp": 1660365254, "time_total_s": 12756.180707454681, "pid": 128228, "hostname": "localhost.localdomain", "node_ip": "192.168.249.74", "config": {"lr": 3.448496205595341e-05, "batch_size": 64, "beta1": 0.9, "beta2": 0.999, "weight_decay": 0.006519728814948943}, "time_since_restore": 12756.180707454681, "timesteps_since_restore": 0, "iterations_since_restore": 20}
{"validation_mean": 0.7965205125191019, "time_this_iter_s": 671.9492259025574, "done": false, "timesteps_total": null, "episodes_total": null, "training_iteration": 21, "trial_id": "a5270_00024", "experiment_id": "b4e564bfe4bd43e3bbadaaaad79855f0", "date": "2022-08-13_12-45-26", "timestamp": 1660365926, "time_total_s": 13428.129933357239, "pid": 128228, "hostname": "localhost.localdomain", "node_ip": "192.168.249.74", "config": {"lr": 3.448496205595341e-05, "batch_size": 64, "beta1": 0.9, "beta2": 0.999, "weight_decay": 0.006519728814948943}, "time_since_restore": 13428.129933357239, "timesteps_since_restore": 0, "iterations_since_restore": 21}
{"validation_mean": 0.7945221582226402, "time_this_iter_s": 672.1117177009583, "done": false, "timesteps_total": null, "episodes_total": null, "training_iteration": 22, "trial_id": "a5270_00024", "experiment_id": "b4e564bfe4bd43e3bbadaaaad79855f0", "date": "2022-08-13_12-56-38", "timestamp": 1660366598, "time_total_s": 14100.241651058197, "pid": 128228, "hostname": "localhost.localdomain", "node_ip": "192.168.249.74", "config": {"lr": 3.448496205595341e-05, "batch_size": 64, "beta1": 0.9, "beta2": 0.999, "weight_decay": 0.006519728814948943}, "time_since_restore": 14100.241651058197, "timesteps_since_restore": 0, "iterations_since_restore": 22}
{"validation_mean": 0.7868226166686259, "time_this_iter_s": 668.7885847091675, "done": false, "timesteps_total": null, "episodes_total": null, "training_iteration": 23, "trial_id": "a5270_00024", "experiment_id": "b4e564bfe4bd43e3bbadaaaad79855f0", "date": "2022-08-13_13-07-47", "timestamp": 1660367267, "time_total_s": 14769.030235767365, "pid": 128228, "hostname": "localhost.localdomain", "node_ip": "192.168.249.74", "config": {"lr": 3.448496205595341e-05, "batch_size": 64, "beta1": 0.9, "beta2": 0.999, "weight_decay": 0.006519728814948943}, "time_since_restore": 14769.030235767365, "timesteps_since_restore": 0, "iterations_since_restore": 23}
{"validation_mean": 0.7885858704596215, "time_this_iter_s": 668.069751739502, "done": false, "timesteps_total": null, "episodes_total": null, "training_iteration": 24, "trial_id": "a5270_00024", "experiment_id": "b4e564bfe4bd43e3bbadaaaad79855f0", "date": "2022-08-13_13-18-55", "timestamp": 1660367935, "time_total_s": 15437.099987506866, "pid": 128228, "hostname": "localhost.localdomain", "node_ip": "192.168.249.74", "config": {"lr": 3.448496205595341e-05, "batch_size": 64, "beta1": 0.9, "beta2": 0.999, "weight_decay": 0.006519728814948943}, "time_since_restore": 15437.099987506866, "timesteps_since_restore": 0, "iterations_since_restore": 24}
{"validation_mean": 0.7673092747149406, "time_this_iter_s": 669.7570426464081, "done": false, "timesteps_total": null, "episodes_total": null, "training_iteration": 25, "trial_id": "a5270_00024", "experiment_id": "b4e564bfe4bd43e3bbadaaaad79855f0", "date": "2022-08-13_13-30-05", "timestamp": 1660368605, "time_total_s": 16106.857030153275, "pid": 128228, "hostname": "localhost.localdomain", "node_ip": "192.168.249.74", "config": {"lr": 3.448496205595341e-05, "batch_size": 64, "beta1": 0.9, "beta2": 0.999, "weight_decay": 0.006519728814948943}, "time_since_restore": 16106.857030153275, "timesteps_since_restore": 0, "iterations_since_restore": 25}
{"validation_mean": 0.7818267309274715, "time_this_iter_s": 668.677841424942, "done": false, "timesteps_total": null, "episodes_total": null, "training_iteration": 26, "trial_id": "a5270_00024", "experiment_id": "b4e564bfe4bd43e3bbadaaaad79855f0", "date": "2022-08-13_13-41-14", "timestamp": 1660369274, "time_total_s": 16775.534871578217, "pid": 128228, "hostname": "localhost.localdomain", "node_ip": "192.168.249.74", "config": {"lr": 3.448496205595341e-05, "batch_size": 64, "beta1": 0.9, "beta2": 0.999, "weight_decay": 0.006519728814948943}, "time_since_restore": 16775.534871578217, "timesteps_since_restore": 0, "iterations_since_restore": 26}
{"validation_mean": 0.7721288350769954, "time_this_iter_s": 668.4438145160675, "done": false, "timesteps_total": null, "episodes_total": null, "training_iteration": 27, "trial_id": "a5270_00024", "experiment_id": "b4e564bfe4bd43e3bbadaaaad79855f0", "date": "2022-08-13_13-52-22", "timestamp": 1660369942, "time_total_s": 17443.978686094284, "pid": 128228, "hostname": "localhost.localdomain", "node_ip": "192.168.249.74", "config": {"lr": 3.448496205595341e-05, "batch_size": 64, "beta1": 0.9, "beta2": 0.999, "weight_decay": 0.006519728814948943}, "time_since_restore": 17443.978686094284, "timesteps_since_restore": 0, "iterations_since_restore": 27}
{"validation_mean": 0.7893499471023863, "time_this_iter_s": 664.212899684906, "done": false, "timesteps_total": null, "episodes_total": null, "training_iteration": 28, "trial_id": "a5270_00024", "experiment_id": "b4e564bfe4bd43e3bbadaaaad79855f0", "date": "2022-08-13_14-03-26", "timestamp": 1660370606, "time_total_s": 18108.19158577919, "pid": 128228, "hostname": "localhost.localdomain", "node_ip": "192.168.249.74", "config": {"lr": 3.448496205595341e-05, "batch_size": 64, "beta1": 0.9, "beta2": 0.999, "weight_decay": 0.006519728814948943}, "time_since_restore": 18108.19158577919, "timesteps_since_restore": 0, "iterations_since_restore": 28}
{"validation_mean": 0.794051957211708, "time_this_iter_s": 667.5251171588898, "done": false, "timesteps_total": null, "episodes_total": null, "training_iteration": 29, "trial_id": "a5270_00024", "experiment_id": "b4e564bfe4bd43e3bbadaaaad79855f0", "date": "2022-08-13_14-14-34", "timestamp": 1660371274, "time_total_s": 18775.71670293808, "pid": 128228, "hostname": "localhost.localdomain", "node_ip": "192.168.249.74", "config": {"lr": 3.448496205595341e-05, "batch_size": 64, "beta1": 0.9, "beta2": 0.999, "weight_decay": 0.006519728814948943}, "time_since_restore": 18775.71670293808, "timesteps_since_restore": 0, "iterations_since_restore": 29}
{"validation_mean": 0.7666039731985423, "time_this_iter_s": 661.4761066436768, "done": true, "timesteps_total": null, "episodes_total": null, "training_iteration": 30, "trial_id": "a5270_00024", "experiment_id": "b4e564bfe4bd43e3bbadaaaad79855f0", "date": "2022-08-13_14-25-35", "timestamp": 1660371935, "time_total_s": 19437.192809581757, "pid": 128228, "hostname": "localhost.localdomain", "node_ip": "192.168.249.74", "config": {"lr": 3.448496205595341e-05, "batch_size": 64, "beta1": 0.9, "beta2": 0.999, "weight_decay": 0.006519728814948943}, "time_since_restore": 19437.192809581757, "timesteps_since_restore": 0, "iterations_since_restore": 30}
