{"validation_mean": 0.484375, "time_this_iter_s": 12.820205688476562, "done": false, "timesteps_total": null, "episodes_total": null, "training_iteration": 1, "trial_id": "a5270_00053", "experiment_id": "e1d8f2c2a9164f91922027be3ef76fc2", "date": "2022-08-14_21-18-50", "timestamp": 1660483130, "time_total_s": 12.820205688476562, "pid": 153680, "hostname": "localhost.localdomain", "node_ip": "192.168.249.74", "config": {"lr": 2.391925335137271e-07, "batch_size": 64, "beta1": 0.9, "beta2": 0.999, "weight_decay": 0.007938813405123656}, "time_since_restore": 12.820205688476562, "timesteps_since_restore": 0, "iterations_since_restore": 1}
{"validation_mean": 0.4994122487363348, "time_this_iter_s": 662.6998333930969, "done": true, "timesteps_total": null, "episodes_total": null, "training_iteration": 2, "trial_id": "a5270_00053", "experiment_id": "e1d8f2c2a9164f91922027be3ef76fc2", "date": "2022-08-14_21-29-53", "timestamp": 1660483793, "time_total_s": 675.5200390815735, "pid": 153680, "hostname": "localhost.localdomain", "node_ip": "192.168.249.74", "config": {"lr": 2.391925335137271e-07, "batch_size": 64, "beta1": 0.9, "beta2": 0.999, "weight_decay": 0.007938813405123656}, "time_since_restore": 675.5200390815735, "timesteps_since_restore": 0, "iterations_since_restore": 2}
